README.md
pyproject.toml
examples/custom_tokenizer/README.md
examples/notebooks/README.md
openmed/__about__.py
openmed/__init__.py
openmed/cli/__init__.py
openmed/cli/main.py
openmed/cli/typer_app.py
openmed/core/__init__.py
openmed/core/config.py
openmed/core/model_registry.py
openmed/core/models.py
openmed/core/pii.py
openmed/core/pii_entity_merger.py
openmed/ner/__init__.py
openmed/ner/adapter.py
openmed/ner/exceptions.py
openmed/ner/indexing.py
openmed/ner/infer.py
openmed/ner/labels.py
openmed/ner/families/__init__.py
openmed/ner/families/base.py
openmed/ner/families/gliner.py
openmed/ner/families/gliner2.py
openmed/processing/__init__.py
openmed/processing/advanced_ner.py
openmed/processing/batch.py
openmed/processing/outputs.py
openmed/processing/sentences.py
openmed/processing/text.py
openmed/processing/tokenization.py
openmed/tui/__init__.py
openmed/tui/app.py
openmed/utils/__init__.py
openmed/utils/logging.py
openmed/utils/profiling.py
openmed/utils/validation.py
openmed/zero_shot/__init__.py
openmed/zero_shot/cli/__init__.py
openmed/zero_shot/cli/index.py
openmed/zero_shot/cli/infer.py
openmed/zero_shot/cli/labels.py
openmed/zero_shot/data/__init__.py
openmed/zero_shot/data/label_maps/__init__.py
openmed/zero_shot/data/label_maps/defaults.json
scripts/README.md
tests/README.md
openmed-0.5.0.dist-info/METADATA
openmed-0.5.0.dist-info/WHEEL
openmed-0.5.0.dist-info/entry_points.txt
openmed-0.5.0.dist-info/licenses/LICENSE
openmed-0.5.0.dist-info/RECORD
